fridonai_core/__init__.py
fridonai_core/crons/__init__.py
fridonai_core/crons/base.py
fridonai_core/crons/registry.py
fridonai_core/graph/__init__.py
fridonai_core/graph/agents.py
fridonai_core/graph/base.py
fridonai_core/graph/chains.py
fridonai_core/graph/models.py
fridonai_core/graph/prompts.py
fridonai_core/graph/routers.py
fridonai_core/graph/schema.py
fridonai_core/graph/states.py
fridonai_core/graph/tools.py
fridonai_core/graph/utils.py
fridonai_core/plugins/README.md
fridonai_core/plugins/__init__.py
fridonai_core/plugins/base.py
fridonai_core/plugins/registry.py
fridonai_core/plugins/schemas.py
fridonai_core/plugins/tools/__init__.py
fridonai_core/plugins/tools/base.py
fridonai_core/plugins/tools/response_dumper_base.py
fridonai_core/plugins/utilities/__init__.py
fridonai_core/plugins/utilities/adapter_base.py
fridonai_core/plugins/utilities/base.py
fridonai_core/plugins/utilities/blockchain.py
fridonai_core/plugins/utilities/llm.py
fridonai_core/plugins/utilities/mock.py
fridonai_core/plugins/utilities/remote.py
fridonai_core-0.0.14.dist-info/METADATA
fridonai_core-0.0.14.dist-info/WHEEL
fridonai_core-0.0.14.dist-info/RECORD
